balderhub/gui/__init__.py
balderhub/gui/_version.py
balderhub/gui/lib/__init__.py
balderhub/gui/lib/scenario_features/__init__.py
balderhub/gui/lib/scenario_features/page_feature.py
balderhub/gui/lib/utils/__init__.py
balderhub/gui/lib/utils/base_selector.py
balderhub/gui/lib/utils/components/__init__.py
balderhub/gui/lib/utils/components/abstract_element.py
balderhub/gui/lib/utils/mixins/__init__.py
balderhub/gui/lib/utils/mixins/circle_mixin.py
balderhub/gui/lib/utils/mixins/clickable_mixin.py
balderhub/gui/lib/utils/mixins/has_value_mixin.py
balderhub/gui/lib/utils/mixins/list_container_mixin.py
balderhub/gui/lib/utils/mixins/paginated_container_mixin.py
balderhub/gui/lib/utils/mixins/rectangle_mixin.py
balderhub/gui/lib/utils/mixins/scrollable_mixin.py
balderhub/gui/lib/utils/mixins/select_by_hidden_value_mixin.py
balderhub/gui/lib/utils/mixins/select_by_index_mixin.py
balderhub/gui/lib/utils/mixins/select_by_visible_text_mixin.py
balderhub/gui/lib/utils/mixins/two_state_checkbox_mixin.py
balderhub/gui/lib/utils/mixins/typeable_mixin.py
balderhub/gui/lib/utils/mixins/visible_mixin.py
balderhub_gui-0.0.1b0.dist-info/licenses/LICENSE
balderhub_gui-0.0.1b0.dist-info/METADATA
balderhub_gui-0.0.1b0.dist-info/WHEEL
balderhub_gui-0.0.1b0.dist-info/top_level.txt
balderhub_gui-0.0.1b0.dist-info/RECORD
